{"ddd":0,"h":24,"w":24,"meta":{"g":"LottieFiles Figma v36"},"layers":[{"ty":4,"sr":1,"st":0,"op":37.090001434786245,"ip":0,"hasMask":false,"ao":0,"ks":{"a":{"a":1,"k":[{"o":{"x":0.65,"y":0},"i":{"x":0.35,"y":0},"s":[7.5,7.5],"t":0},{"o":{"x":0.65,"y":0},"i":{"x":0.35,"y":0},"s":[7.5,7.5],"t":0.03000000142492354},{"o":{"x":0.65,"y":0},"i":{"x":0.35,"y":0},"s":[1,1],"t":18.03000071668066},{"o":{"x":0.65,"y":0},"i":{"x":0.35,"y":0},"s":[1,1],"t":18.060000718105584},{"o":{"x":0,"y":0},"i":{"x":1,"y":1},"s":[7.5,7.5],"t":36.06000143336132},{"s":[7.5,7.5],"t":36.090001434786245}]},"s":{"a":1,"k":[{"o":{"x":0.65,"y":0},"i":{"x":0.35,"y":0},"s":[100,100],"t":0},{"o":{"x":0.65,"y":0},"i":{"x":0.35,"y":0},"s":[100,100],"t":0.03000000142492354},{"o":{"x":0.65,"y":0},"i":{"x":0.35,"y":0},"s":[100,100],"t":18.03000071668066},{"o":{"x":0.65,"y":0},"i":{"x":0.35,"y":0},"s":[100,100],"t":18.060000718105584},{"o":{"x":0,"y":0},"i":{"x":1,"y":1},"s":[100,100],"t":36.06000143336132},{"s":[100,100],"t":36.090001434786245}]},"p":{"a":1,"k":[{"o":{"x":0.65,"y":0},"i":{"x":0.35,"y":0},"s":[12,12],"t":0},{"o":{"x":0.65,"y":0},"i":{"x":0.35,"y":0},"s":[12,12],"t":0.03000000142492354},{"o":{"x":0.65,"y":0},"i":{"x":0.35,"y":0},"s":[12,12],"t":18.03000071668066},{"o":{"x":0.65,"y":0},"i":{"x":0.35,"y":0},"s":[12,12],"t":18.060000718105584},{"o":{"x":0,"y":0},"i":{"x":1,"y":1},"s":[12,12],"t":36.06000143336132},{"s":[12,12],"t":36.090001434786245}]},"r":{"a":1,"k":[{"o":{"x":0.65,"y":0},"i":{"x":0.35,"y":0},"s":[0],"t":0},{"o":{"x":0.65,"y":0},"i":{"x":0.35,"y":0},"s":[0],"t":0.03000000142492354},{"o":{"x":0.65,"y":0},"i":{"x":0.35,"y":0},"s":[0],"t":18.03000071668066},{"o":{"x":0.65,"y":0},"i":{"x":0.35,"y":0},"s":[0],"t":18.060000718105584},{"o":{"x":0,"y":0},"i":{"x":1,"y":1},"s":[0],"t":36.06000143336132},{"s":[0],"t":36.090001434786245}]},"o":{"a":1,"k":[{"o":{"x":0.65,"y":0},"i":{"x":0.35,"y":0},"s":[100],"t":0},{"o":{"x":0.65,"y":0},"i":{"x":0.35,"y":0},"s":[100],"t":0.03000000142492354},{"o":{"x":0.65,"y":0},"i":{"x":0.35,"y":0},"s":[100],"t":18.03000071668066},{"o":{"x":0.65,"y":0},"i":{"x":0.35,"y":0},"s":[100],"t":18.060000718105584},{"o":{"x":0,"y":0},"i":{"x":1,"y":1},"s":[100],"t":36.06000143336132},{"s":[100],"t":36.090001434786245}]}},"shapes":[{"ty":"sh","d":1,"ks":{"a":1,"k":[{"o":{"x":0.65,"y":0},"i":{"x":0.35,"y":0},"s":[{"c":true,"i":[[0,0],[0,4.14],[4.14,0],[0,-4.14],[-4.14,0]],"o":[[4.14,0],[0,-4.14],[-4.14,0],[0,4.14],[0,0]],"v":[[7.5,15],[15,7.5],[7.5,0],[0,7.5],[7.5,15]]}],"t":0},{"o":{"x":0.65,"y":0},"i":{"x":0.35,"y":0},"s":[{"c":true,"i":[[0,0],[0,4.14],[4.14,0],[0,-4.14],[-4.14,0]],"o":[[4.14,0],[0,-4.14],[-4.14,0],[0,4.14],[0,0]],"v":[[7.5,15],[15,7.5],[7.5,0],[0,7.5],[7.5,15]]}],"t":0.03000000142492354},{"o":{"x":0.65,"y":0},"i":{"x":0.35,"y":0},"s":[{"c":true,"i":[[0,0],[0,0.55],[0.55,0],[0,-0.55],[-0.55,0]],"o":[[0.55,0],[0,-0.55],[-0.55,0],[0,0.55],[0,0]],"v":[[1,2],[2,1],[1,0],[0,1],[1,2]]}],"t":18.03000071668066},{"o":{"x":0.65,"y":0},"i":{"x":0.35,"y":0},"s":[{"c":true,"i":[[0,0],[0,0.55],[0.55,0],[0,-0.55],[-0.55,0]],"o":[[0.55,0],[0,-0.55],[-0.55,0],[0,0.55],[0,0]],"v":[[1,2],[2,1],[1,0],[0,1],[1,2]]}],"t":18.060000718105584},{"o":{"x":0,"y":0},"i":{"x":1,"y":1},"s":[{"c":true,"i":[[0,0],[0,4.14],[4.14,0],[0,-4.14],[-4.14,0]],"o":[[4.14,0],[0,-4.14],[-4.14,0],[0,4.14],[0,0]],"v":[[7.5,15],[15,7.5],[7.5,0],[0,7.5],[7.5,15]]}],"t":36.06000143336132},{"s":[{"c":true,"i":[[0,0],[0,4.14],[4.14,0],[0,-4.14],[-4.14,0]],"o":[[4.14,0],[0,-4.14],[-4.14,0],[0,4.14],[0,0]],"v":[[7.5,15],[15,7.5],[7.5,0],[0,7.5],[7.5,15]]}],"t":36.090001434786245}]}},{"ty":"sh","d":1,"ks":{"a":1,"k":[{"o":{"x":0.65,"y":0},"i":{"x":0.35,"y":0},"s":[{"c":true,"i":[[0,0],[0.66,0.66],[0,0.93],[-0.66,0.66],[-0.93,0],[-0.66,-0.66],[0,-0.93],[0.66,-0.66],[0.93,0]],"o":[[-0.93,0],[-0.66,-0.66],[0,-0.93],[0.66,-0.66],[0.93,0],[0.66,0.66],[0,0.93],[-0.66,0.66],[0,0]],"v":[[7.5,11],[5.03,9.97],[4,7.5],[5.03,5.03],[7.5,4],[9.97,5.03],[11,7.5],[9.97,9.97],[7.5,11]]}],"t":0},{"o":{"x":0.65,"y":0},"i":{"x":0.35,"y":0},"s":[{"c":true,"i":[[0,0],[0.66,0.66],[0,0.93],[-0.66,0.66],[-0.93,0],[-0.66,-0.66],[0,-0.93],[0.66,-0.66],[0.93,0]],"o":[[-0.93,0],[-0.66,-0.66],[0,-0.93],[0.66,-0.66],[0.93,0],[0.66,0.66],[0,0.93],[-0.66,0.66],[0,0]],"v":[[7.5,11],[5.03,9.97],[4,7.5],[5.03,5.03],[7.5,4],[9.97,5.03],[11,7.5],[9.97,9.97],[7.5,11]]}],"t":0.03000000142492354},{"o":{"x":0.65,"y":0},"i":{"x":0.35,"y":0},"s":[{"c":true,"i":[[0,0],[0.09,0.09],[0,0.12],[-0.09,0.09],[-0.12,0],[-0.09,-0.09],[0,-0.12],[0.09,-0.09],[0.12,0]],"o":[[-0.12,0],[-0.09,-0.09],[0,-0.12],[0.09,-0.09],[0.12,0],[0.09,0.09],[0,0.12],[-0.09,0.09],[0,0]],"v":[[1,1.47],[0.67,1.33],[0.53,1],[0.67,0.67],[1,0.53],[1.33,0.67],[1.47,1],[1.33,1.33],[1,1.47]]}],"t":18.03000071668066},{"o":{"x":0.65,"y":0},"i":{"x":0.35,"y":0},"s":[{"c":true,"i":[[0,0],[0.09,0.09],[0,0.12],[-0.09,0.09],[-0.12,0],[-0.09,-0.09],[0,-0.12],[0.09,-0.09],[0.12,0]],"o":[[-0.12,0],[-0.09,-0.09],[0,-0.12],[0.09,-0.09],[0.12,0],[0.09,0.09],[0,0.12],[-0.09,0.09],[0,0]],"v":[[1,1.47],[0.67,1.33],[0.53,1],[0.67,0.67],[1,0.53],[1.33,0.67],[1.47,1],[1.33,1.33],[1,1.47]]}],"t":18.060000718105584},{"o":{"x":0,"y":0},"i":{"x":1,"y":1},"s":[{"c":true,"i":[[0,0],[0.66,0.66],[0,0.93],[-0.66,0.66],[-0.93,0],[-0.66,-0.66],[0,-0.93],[0.66,-0.66],[0.93,0]],"o":[[-0.93,0],[-0.66,-0.66],[0,-0.93],[0.66,-0.66],[0.93,0],[0.66,0.66],[0,0.93],[-0.66,0.66],[0,0]],"v":[[7.5,11],[5.03,9.97],[4,7.5],[5.03,5.03],[7.5,4],[9.97,5.03],[11,7.5],[9.97,9.97],[7.5,11]]}],"t":36.06000143336132},{"s":[{"c":true,"i":[[0,0],[0.66,0.66],[0,0.93],[-0.66,0.66],[-0.93,0],[-0.66,-0.66],[0,-0.93],[0.66,-0.66],[0.93,0]],"o":[[-0.93,0],[-0.66,-0.66],[0,-0.93],[0.66,-0.66],[0.93,0],[0.66,0.66],[0,0.93],[-0.66,0.66],[0,0]],"v":[[7.5,11],[5.03,9.97],[4,7.5],[5.03,5.03],[7.5,4],[9.97,5.03],[11,7.5],[9.97,9.97],[7.5,11]]}],"t":36.090001434786245}]}},{"ty":"fl","c":{"a":1,"k":[{"o":{"x":0.65,"y":0},"i":{"x":0.35,"y":0},"s":[0,0,0],"t":0},{"o":{"x":0.65,"y":0},"i":{"x":0.35,"y":0},"s":[0,0,0],"t":0.03000000142492354},{"o":{"x":0.65,"y":0},"i":{"x":0.35,"y":0},"s":[0,0,0],"t":18.03000071668066},{"o":{"x":0.65,"y":0},"i":{"x":0.35,"y":0},"s":[0,0,0],"t":18.060000718105584},{"o":{"x":0,"y":0},"i":{"x":1,"y":1},"s":[0,0,0],"t":36.06000143336132},{"s":[0,0,0],"t":36.090001434786245}]},"r":2,"o":{"a":1,"k":[{"o":{"x":0.65,"y":0},"i":{"x":0.35,"y":0},"s":[100],"t":0},{"o":{"x":0.65,"y":0},"i":{"x":0.35,"y":0},"s":[100],"t":0.03000000142492354},{"o":{"x":0.65,"y":0},"i":{"x":0.35,"y":0},"s":[100],"t":18.03000071668066},{"o":{"x":0.65,"y":0},"i":{"x":0.35,"y":0},"s":[100],"t":18.060000718105584},{"o":{"x":0,"y":0},"i":{"x":1,"y":1},"s":[100],"t":36.06000143336132},{"s":[100],"t":36.090001434786245}]}}],"ind":1},{"ty":4,"sr":1,"st":0,"op":37.090001434786245,"ip":0,"hasMask":false,"ao":0,"ks":{"a":{"a":1,"k":[{"o":{"x":0.65,"y":0},"i":{"x":0.35,"y":0},"s":[2.5,3.25],"t":0},{"o":{"x":0.65,"y":0},"i":{"x":0.35,"y":0},"s":[2.5,3.25],"t":0.03000000142492354},{"o":{"x":0.65,"y":0},"i":{"x":0.35,"y":0},"s":[1,4.5],"t":18.03000071668066},{"o":{"x":0.65,"y":0},"i":{"x":0.35,"y":0},"s":[1,4.5],"t":18.060000718105584},{"o":{"x":0,"y":0},"i":{"x":1,"y":1},"s":[2.5,3.25],"t":36.06000143336132},{"s":[2.5,3.25],"t":36.090001434786245}]},"s":{"a":1,"k":[{"o":{"x":0.65,"y":0},"i":{"x":0.35,"y":0},"s":[100,100],"t":0},{"o":{"x":0.65,"y":0},"i":{"x":0.35,"y":0},"s":[100,100],"t":0.03000000142492354},{"o":{"x":0.65,"y":0},"i":{"x":0.35,"y":0},"s":[100,100],"t":18.03000071668066},{"o":{"x":0.65,"y":0},"i":{"x":0.35,"y":0},"s":[100,100],"t":18.060000718105584},{"o":{"x":0,"y":0},"i":{"x":1,"y":1},"s":[100,100],"t":36.06000143336132},{"s":[100,100],"t":36.090001434786245}]},"p":{"a":1,"k":[{"o":{"x":0.65,"y":0},"i":{"x":0.35,"y":0},"s":[17.85,15.38],"t":0},{"o":{"x":0.65,"y":0},"i":{"x":0.35,"y":0},"s":[17.85,15.38],"t":0.03000000142492354},{"o":{"x":0.65,"y":0},"i":{"x":0.35,"y":0},"s":[15.18,15.18],"t":18.03000071668066},{"o":{"x":0.65,"y":0},"i":{"x":0.35,"y":0},"s":[15.18,15.18],"t":18.060000718105584},{"o":{"x":0,"y":0},"i":{"x":1,"y":1},"s":[17.85,15.38],"t":36.06000143336132},{"s":[17.85,15.38],"t":36.090001434786245}]},"r":{"a":1,"k":[{"o":{"x":0.65,"y":0},"i":{"x":0.35,"y":0},"s":[-60],"t":0},{"o":{"x":0.65,"y":0},"i":{"x":0.35,"y":0},"s":[-60],"t":0.03000000142492354},{"o":{"x":0.65,"y":0},"i":{"x":0.35,"y":0},"s":[-45],"t":18.03000071668066},{"o":{"x":0.65,"y":0},"i":{"x":0.35,"y":0},"s":[-45],"t":18.060000718105584},{"o":{"x":0,"y":0},"i":{"x":1,"y":1},"s":[-60],"t":36.06000143336132},{"s":[-60],"t":36.090001434786245}]},"o":{"a":1,"k":[{"o":{"x":0.65,"y":0},"i":{"x":0.35,"y":0},"s":[100],"t":0},{"o":{"x":0.65,"y":0},"i":{"x":0.35,"y":0},"s":[100],"t":0.03000000142492354},{"o":{"x":0.65,"y":0},"i":{"x":0.35,"y":0},"s":[100],"t":18.03000071668066},{"o":{"x":0.65,"y":0},"i":{"x":0.35,"y":0},"s":[100],"t":18.060000718105584},{"o":{"x":0,"y":0},"i":{"x":1,"y":1},"s":[100],"t":36.06000143336132},{"s":[100],"t":36.090001434786245}]}},"shapes":[{"ty":"sh","d":1,"ks":{"a":1,"k":[{"o":{"x":0.65,"y":0},"i":{"x":0.35,"y":0},"s":[{"c":true,"i":[[0,0],[-0.55,0],[0,0],[0,-0.55],[0,0],[0.55,0],[0,0],[0,0.55]],"o":[[0,-0.55],[0,0],[0.55,0],[0,0],[0,0.55],[0,0],[-0.55,0],[0,0]],"v":[[0,1],[1,0],[4,0],[5,1],[5,5.5],[4,6.5],[1,6.5],[0,5.5]]}],"t":0},{"o":{"x":0.65,"y":0},"i":{"x":0.35,"y":0},"s":[{"c":true,"i":[[0,0],[-0.55,0],[0,0],[0,-0.55],[0,0],[0.55,0],[0,0],[0,0.55]],"o":[[0,-0.55],[0,0],[0.55,0],[0,0],[0,0.55],[0,0],[-0.55,0],[0,0]],"v":[[0,1],[1,0],[4,0],[5,1],[5,5.5],[4,6.5],[1,6.5],[0,5.5]]}],"t":0.03000000142492354},{"o":{"x":0.65,"y":0},"i":{"x":0.35,"y":0},"s":[{"c":true,"i":[[0,0],[0,0],[0,0],[0,0],[0,0],[0,0],[0,0],[0,0]],"o":[[0,0],[0,0],[0,0],[0,0],[0,0],[0,0],[0,0],[0,0]],"v":[[0,0],[0,0],[2,0],[2,0],[2,9],[2,9],[0,9],[0,9]]}],"t":18.03000071668066},{"o":{"x":0.65,"y":0},"i":{"x":0.35,"y":0},"s":[{"c":true,"i":[[0,0],[0,0],[0,0],[0,0],[0,0],[0,0],[0,0],[0,0]],"o":[[0,0],[0,0],[0,0],[0,0],[0,0],[0,0],[0,0],[0,0]],"v":[[0,0],[0,0],[2,0],[2,0],[2,9],[2,9],[0,9],[0,9]]}],"t":18.060000718105584},{"o":{"x":0,"y":0},"i":{"x":1,"y":1},"s":[{"c":true,"i":[[0,0],[-0.55,0],[0,0],[0,-0.55],[0,0],[0.55,0],[0,0],[0,0.55]],"o":[[0,-0.55],[0,0],[0.55,0],[0,0],[0,0.55],[0,0],[-0.55,0],[0,0]],"v":[[0,1],[1,0],[4,0],[5,1],[5,5.5],[4,6.5],[1,6.5],[0,5.5]]}],"t":36.06000143336132},{"s":[{"c":true,"i":[[0,0],[-0.55,0],[0,0],[0,-0.55],[0,0],[0.55,0],[0,0],[0,0.55]],"o":[[0,-0.55],[0,0],[0.55,0],[0,0],[0,0.55],[0,0],[-0.55,0],[0,0]],"v":[[0,1],[1,0],[4,0],[5,1],[5,5.5],[4,6.5],[1,6.5],[0,5.5]]}],"t":36.090001434786245}]}},{"ty":"fl","c":{"a":1,"k":[{"o":{"x":0.65,"y":0},"i":{"x":0.35,"y":0},"s":[0,0,0],"t":0},{"o":{"x":0.65,"y":0},"i":{"x":0.35,"y":0},"s":[0,0,0],"t":0.03000000142492354},{"o":{"x":0.65,"y":0},"i":{"x":0.35,"y":0},"s":[0,0,0],"t":18.03000071668066},{"o":{"x":0.65,"y":0},"i":{"x":0.35,"y":0},"s":[0,0,0],"t":18.060000718105584},{"o":{"x":0,"y":0},"i":{"x":1,"y":1},"s":[0,0,0],"t":36.06000143336132},{"s":[0,0,0],"t":36.090001434786245}]},"r":1,"o":{"a":1,"k":[{"o":{"x":0.65,"y":0},"i":{"x":0.35,"y":0},"s":[100],"t":0},{"o":{"x":0.65,"y":0},"i":{"x":0.35,"y":0},"s":[100],"t":0.03000000142492354},{"o":{"x":0.65,"y":0},"i":{"x":0.35,"y":0},"s":[100],"t":18.03000071668066},{"o":{"x":0.65,"y":0},"i":{"x":0.35,"y":0},"s":[100],"t":18.060000718105584},{"o":{"x":0,"y":0},"i":{"x":1,"y":1},"s":[100],"t":36.06000143336132},{"s":[100],"t":36.090001434786245}]}}],"ind":2},{"ty":4,"sr":1,"st":0,"op":37.090001434786245,"ip":0,"hasMask":false,"ao":0,"ks":{"a":{"a":1,"k":[{"o":{"x":0.65,"y":0},"i":{"x":0.35,"y":0},"s":[2.5,3.25],"t":0},{"o":{"x":0.65,"y":0},"i":{"x":0.35,"y":0},"s":[2.5,3.25],"t":0.03000000142492354},{"o":{"x":0.65,"y":0},"i":{"x":0.35,"y":0},"s":[1,4.5],"t":18.03000071668066},{"o":{"x":0.65,"y":0},"i":{"x":0.35,"y":0},"s":[1,4.5],"t":18.060000718105584},{"o":{"x":0,"y":0},"i":{"x":1,"y":1},"s":[2.5,3.25],"t":36.06000143336132},{"s":[2.5,3.25],"t":36.090001434786245}]},"s":{"a":1,"k":[{"o":{"x":0.65,"y":0},"i":{"x":0.35,"y":0},"s":[100,100],"t":0},{"o":{"x":0.65,"y":0},"i":{"x":0.35,"y":0},"s":[100,100],"t":0.03000000142492354},{"o":{"x":0.65,"y":0},"i":{"x":0.35,"y":0},"s":[100,100],"t":18.03000071668066},{"o":{"x":0.65,"y":0},"i":{"x":0.35,"y":0},"s":[100,100],"t":18.060000718105584},{"o":{"x":0,"y":0},"i":{"x":1,"y":1},"s":[100,100],"t":36.06000143336132},{"s":[100,100],"t":36.090001434786245}]},"p":{"a":1,"k":[{"o":{"x":0.65,"y":0},"i":{"x":0.35,"y":0},"s":[6.15,15.37],"t":0},{"o":{"x":0.65,"y":0},"i":{"x":0.35,"y":0},"s":[6.15,15.37],"t":0.03000000142492354},{"o":{"x":0.65,"y":0},"i":{"x":0.35,"y":0},"s":[8.82,15.18],"t":18.03000071668066},{"o":{"x":0.65,"y":0},"i":{"x":0.35,"y":0},"s":[8.82,15.18],"t":18.060000718105584},{"o":{"x":0,"y":0},"i":{"x":1,"y":1},"s":[6.15,15.37],"t":36.06000143336132},{"s":[6.15,15.37],"t":36.090001434786245}]},"r":{"a":1,"k":[{"o":{"x":0.65,"y":0},"i":{"x":0.35,"y":0},"s":[60],"t":0},{"o":{"x":0.65,"y":0},"i":{"x":0.35,"y":0},"s":[60],"t":0.03000000142492354},{"o":{"x":0.65,"y":0},"i":{"x":0.35,"y":0},"s":[45],"t":18.03000071668066},{"o":{"x":0.65,"y":0},"i":{"x":0.35,"y":0},"s":[45],"t":18.060000718105584},{"o":{"x":0,"y":0},"i":{"x":1,"y":1},"s":[60],"t":36.06000143336132},{"s":[60],"t":36.090001434786245}]},"o":{"a":1,"k":[{"o":{"x":0.65,"y":0},"i":{"x":0.35,"y":0},"s":[100],"t":0},{"o":{"x":0.65,"y":0},"i":{"x":0.35,"y":0},"s":[100],"t":0.03000000142492354},{"o":{"x":0.65,"y":0},"i":{"x":0.35,"y":0},"s":[100],"t":18.03000071668066},{"o":{"x":0.65,"y":0},"i":{"x":0.35,"y":0},"s":[100],"t":18.060000718105584},{"o":{"x":0,"y":0},"i":{"x":1,"y":1},"s":[100],"t":36.06000143336132},{"s":[100],"t":36.090001434786245}]}},"shapes":[{"ty":"sh","d":1,"ks":{"a":1,"k":[{"o":{"x":0.65,"y":0},"i":{"x":0.35,"y":0},"s":[{"c":true,"i":[[0,0],[-0.55,0],[0,0],[0,-0.55],[0,0],[0.55,0],[0,0],[0,0.55]],"o":[[0,-0.55],[0,0],[0.55,0],[0,0],[0,0.55],[0,0],[-0.55,0],[0,0]],"v":[[0,1],[1,0],[4,0],[5,1],[5,5.5],[4,6.5],[1,6.5],[0,5.5]]}],"t":0},{"o":{"x":0.65,"y":0},"i":{"x":0.35,"y":0},"s":[{"c":true,"i":[[0,0],[-0.55,0],[0,0],[0,-0.55],[0,0],[0.55,0],[0,0],[0,0.55]],"o":[[0,-0.55],[0,0],[0.55,0],[0,0],[0,0.55],[0,0],[-0.55,0],[0,0]],"v":[[0,1],[1,0],[4,0],[5,1],[5,5.5],[4,6.5],[1,6.5],[0,5.5]]}],"t":0.03000000142492354},{"o":{"x":0.65,"y":0},"i":{"x":0.35,"y":0},"s":[{"c":true,"i":[[0,0],[0,0],[0,0],[0,0],[0,0],[0,0],[0,0],[0,0]],"o":[[0,0],[0,0],[0,0],[0,0],[0,0],[0,0],[0,0],[0,0]],"v":[[0,0],[0,0],[2,0],[2,0],[2,9],[2,9],[0,9],[0,9]]}],"t":18.03000071668066},{"o":{"x":0.65,"y":0},"i":{"x":0.35,"y":0},"s":[{"c":true,"i":[[0,0],[0,0],[0,0],[0,0],[0,0],[0,0],[0,0],[0,0]],"o":[[0,0],[0,0],[0,0],[0,0],[0,0],[0,0],[0,0],[0,0]],"v":[[0,0],[0,0],[2,0],[2,0],[2,9],[2,9],[0,9],[0,9]]}],"t":18.060000718105584},{"o":{"x":0,"y":0},"i":{"x":1,"y":1},"s":[{"c":true,"i":[[0,0],[-0.55,0],[0,0],[0,-0.55],[0,0],[0.55,0],[0,0],[0,0.55]],"o":[[0,-0.55],[0,0],[0.55,0],[0,0],[0,0.55],[0,0],[-0.55,0],[0,0]],"v":[[0,1],[1,0],[4,0],[5,1],[5,5.5],[4,6.5],[1,6.5],[0,5.5]]}],"t":36.06000143336132},{"s":[{"c":true,"i":[[0,0],[-0.55,0],[0,0],[0,-0.55],[0,0],[0.55,0],[0,0],[0,0.55]],"o":[[0,-0.55],[0,0],[0.55,0],[0,0],[0,0.55],[0,0],[-0.55,0],[0,0]],"v":[[0,1],[1,0],[4,0],[5,1],[5,5.5],[4,6.5],[1,6.5],[0,5.5]]}],"t":36.090001434786245}]}},{"ty":"fl","c":{"a":1,"k":[{"o":{"x":0.65,"y":0},"i":{"x":0.35,"y":0},"s":[0,0,0],"t":0},{"o":{"x":0.65,"y":0},"i":{"x":0.35,"y":0},"s":[0,0,0],"t":0.03000000142492354},{"o":{"x":0.65,"y":0},"i":{"x":0.35,"y":0},"s":[0,0,0],"t":18.03000071668066},{"o":{"x":0.65,"y":0},"i":{"x":0.35,"y":0},"s":[0,0,0],"t":18.060000718105584},{"o":{"x":0,"y":0},"i":{"x":1,"y":1},"s":[0,0,0],"t":36.06000143336132},{"s":[0,0,0],"t":36.090001434786245}]},"r":1,"o":{"a":1,"k":[{"o":{"x":0.65,"y":0},"i":{"x":0.35,"y":0},"s":[100],"t":0},{"o":{"x":0.65,"y":0},"i":{"x":0.35,"y":0},"s":[100],"t":0.03000000142492354},{"o":{"x":0.65,"y":0},"i":{"x":0.35,"y":0},"s":[100],"t":18.03000071668066},{"o":{"x":0.65,"y":0},"i":{"x":0.35,"y":0},"s":[100],"t":18.060000718105584},{"o":{"x":0,"y":0},"i":{"x":1,"y":1},"s":[100],"t":36.06000143336132},{"s":[100],"t":36.090001434786245}]}}],"ind":3},{"ty":4,"sr":1,"st":0,"op":37.090001434786245,"ip":0,"hasMask":false,"ao":0,"ks":{"a":{"a":1,"k":[{"o":{"x":0.65,"y":0},"i":{"x":0.35,"y":0},"s":[2.5,3.25],"t":0},{"o":{"x":0.65,"y":0},"i":{"x":0.35,"y":0},"s":[2.5,3.25],"t":0.03000000142492354},{"o":{"x":0.65,"y":0},"i":{"x":0.35,"y":0},"s":[1,0.5],"t":18.03000071668066},{"o":{"x":0.65,"y":0},"i":{"x":0.35,"y":0},"s":[1,0.5],"t":18.060000718105584},{"o":{"x":0,"y":0},"i":{"x":1,"y":1},"s":[2.5,3.25],"t":36.06000143336132},{"s":[2.5,3.25],"t":36.090001434786245}]},"s":{"a":1,"k":[{"o":{"x":0.65,"y":0},"i":{"x":0.35,"y":0},"s":[100,100],"t":0},{"o":{"x":0.65,"y":0},"i":{"x":0.35,"y":0},"s":[100,100],"t":0.03000000142492354},{"o":{"x":0.65,"y":0},"i":{"x":0.35,"y":0},"s":[100,100],"t":18.03000071668066},{"o":{"x":0.65,"y":0},"i":{"x":0.35,"y":0},"s":[100,100],"t":18.060000718105584},{"o":{"x":0,"y":0},"i":{"x":1,"y":1},"s":[100,100],"t":36.06000143336132},{"s":[100,100],"t":36.090001434786245}]},"p":{"a":1,"k":[{"o":{"x":0.65,"y":0},"i":{"x":0.35,"y":0},"s":[12,18.75],"t":0},{"o":{"x":0.65,"y":0},"i":{"x":0.35,"y":0},"s":[12,18.75],"t":0.03000000142492354},{"o":{"x":0.65,"y":0},"i":{"x":0.35,"y":0},"s":[12,12.5],"t":18.03000071668066},{"o":{"x":0.65,"y":0},"i":{"x":0.35,"y":0},"s":[12,12.5],"t":18.060000718105584},{"o":{"x":0,"y":0},"i":{"x":1,"y":1},"s":[12,18.75],"t":36.06000143336132},{"s":[12,18.75],"t":36.090001434786245}]},"r":{"a":1,"k":[{"o":{"x":0.65,"y":0},"i":{"x":0.35,"y":0},"s":[0],"t":0},{"o":{"x":0.65,"y":0},"i":{"x":0.35,"y":0},"s":[0],"t":0.03000000142492354},{"o":{"x":0.65,"y":0},"i":{"x":0.35,"y":0},"s":[0],"t":18.03000071668066},{"o":{"x":0.65,"y":0},"i":{"x":0.35,"y":0},"s":[0],"t":18.060000718105584},{"o":{"x":0,"y":0},"i":{"x":1,"y":1},"s":[0],"t":36.06000143336132},{"s":[0],"t":36.090001434786245}]},"o":{"a":1,"k":[{"o":{"x":0.65,"y":0},"i":{"x":0.35,"y":0},"s":[100],"t":0},{"o":{"x":0.65,"y":0},"i":{"x":0.35,"y":0},"s":[100],"t":0.03000000142492354},{"o":{"x":0.65,"y":0},"i":{"x":0.35,"y":0},"s":[100],"t":18.03000071668066},{"o":{"x":0.65,"y":0},"i":{"x":0.35,"y":0},"s":[100],"t":18.060000718105584},{"o":{"x":0,"y":0},"i":{"x":1,"y":1},"s":[100],"t":36.06000143336132},{"s":[100],"t":36.090001434786245}]}},"shapes":[{"ty":"sh","d":1,"ks":{"a":1,"k":[{"o":{"x":0.65,"y":0},"i":{"x":0.35,"y":0},"s":[{"c":true,"i":[[0,0],[-0.55,0],[0,0],[0,-0.55],[0,0],[0.55,0],[0,0],[0,0.55]],"o":[[0,-0.55],[0,0],[0.55,0],[0,0],[0,0.55],[0,0],[-0.55,0],[0,0]],"v":[[0,1],[1,0],[4,0],[5,1],[5,5.5],[4,6.5],[1,6.5],[0,5.5]]}],"t":0},{"o":{"x":0.65,"y":0},"i":{"x":0.35,"y":0},"s":[{"c":true,"i":[[0,0],[-0.55,0],[0,0],[0,-0.55],[0,0],[0.55,0],[0,0],[0,0.55]],"o":[[0,-0.55],[0,0],[0.55,0],[0,0],[0,0.55],[0,0],[-0.55,0],[0,0]],"v":[[0,1],[1,0],[4,0],[5,1],[5,5.5],[4,6.5],[1,6.5],[0,5.5]]}],"t":0.03000000142492354},{"o":{"x":0.65,"y":0},"i":{"x":0.35,"y":0},"s":[{"c":true,"i":[[0,0],[0,0],[0,0],[0,0],[0,0],[0,0],[0,0],[0,0]],"o":[[0,0],[0,0],[0,0],[0,0],[0,0],[0,0],[0,0],[0,0]],"v":[[0,0],[0,0],[2,0],[2,0],[2,1],[2,1],[0,1],[0,1]]}],"t":18.03000071668066},{"o":{"x":0.65,"y":0},"i":{"x":0.35,"y":0},"s":[{"c":true,"i":[[0,0],[0,0],[0,0],[0,0],[0,0],[0,0],[0,0],[0,0]],"o":[[0,0],[0,0],[0,0],[0,0],[0,0],[0,0],[0,0],[0,0]],"v":[[0,0],[0,0],[2,0],[2,0],[2,1],[2,1],[0,1],[0,1]]}],"t":18.060000718105584},{"o":{"x":0,"y":0},"i":{"x":1,"y":1},"s":[{"c":true,"i":[[0,0],[-0.55,0],[0,0],[0,-0.55],[0,0],[0.55,0],[0,0],[0,0.55]],"o":[[0,-0.55],[0,0],[0.55,0],[0,0],[0,0.55],[0,0],[-0.55,0],[0,0]],"v":[[0,1],[1,0],[4,0],[5,1],[5,5.5],[4,6.5],[1,6.5],[0,5.5]]}],"t":36.06000143336132},{"s":[{"c":true,"i":[[0,0],[-0.55,0],[0,0],[0,-0.55],[0,0],[0.55,0],[0,0],[0,0.55]],"o":[[0,-0.55],[0,0],[0.55,0],[0,0],[0,0.55],[0,0],[-0.55,0],[0,0]],"v":[[0,1],[1,0],[4,0],[5,1],[5,5.5],[4,6.5],[1,6.5],[0,5.5]]}],"t":36.090001434786245}]}},{"ty":"fl","c":{"a":1,"k":[{"o":{"x":0.65,"y":0},"i":{"x":0.35,"y":0},"s":[0,0,0],"t":0},{"o":{"x":0.65,"y":0},"i":{"x":0.35,"y":0},"s":[0,0,0],"t":0.03000000142492354},{"o":{"x":0.65,"y":0},"i":{"x":0.35,"y":0},"s":[0,0,0],"t":18.03000071668066},{"o":{"x":0.65,"y":0},"i":{"x":0.35,"y":0},"s":[0,0,0],"t":18.060000718105584},{"o":{"x":0,"y":0},"i":{"x":1,"y":1},"s":[0,0,0],"t":36.06000143336132},{"s":[0,0,0],"t":36.090001434786245}]},"r":1,"o":{"a":1,"k":[{"o":{"x":0.65,"y":0},"i":{"x":0.35,"y":0},"s":[100],"t":0},{"o":{"x":0.65,"y":0},"i":{"x":0.35,"y":0},"s":[100],"t":0.03000000142492354},{"o":{"x":0.65,"y":0},"i":{"x":0.35,"y":0},"s":[100],"t":18.03000071668066},{"o":{"x":0.65,"y":0},"i":{"x":0.35,"y":0},"s":[100],"t":18.060000718105584},{"o":{"x":0,"y":0},"i":{"x":1,"y":1},"s":[100],"t":36.06000143336132},{"s":[100],"t":36.090001434786245}]}}],"ind":4},{"ty":4,"sr":1,"st":0,"op":37.090001434786245,"ip":0,"hasMask":false,"ao":0,"ks":{"a":{"a":1,"k":[{"o":{"x":0.65,"y":0},"i":{"x":0.35,"y":0},"s":[2.5,3.25],"t":0},{"o":{"x":0.65,"y":0},"i":{"x":0.35,"y":0},"s":[2.5,3.25],"t":0.03000000142492354},{"o":{"x":0.65,"y":0},"i":{"x":0.35,"y":0},"s":[1,4.5],"t":18.03000071668066},{"o":{"x":0.65,"y":0},"i":{"x":0.35,"y":0},"s":[1,4.5],"t":18.060000718105584},{"o":{"x":0,"y":0},"i":{"x":1,"y":1},"s":[2.5,3.25],"t":36.06000143336132},{"s":[2.5,3.25],"t":36.090001434786245}]},"s":{"a":1,"k":[{"o":{"x":0.65,"y":0},"i":{"x":0.35,"y":0},"s":[100,100],"t":0},{"o":{"x":0.65,"y":0},"i":{"x":0.35,"y":0},"s":[100,100],"t":0.03000000142492354},{"o":{"x":0.65,"y":0},"i":{"x":0.35,"y":0},"s":[100,100],"t":18.03000071668066},{"o":{"x":0.65,"y":0},"i":{"x":0.35,"y":0},"s":[100,100],"t":18.060000718105584},{"o":{"x":0,"y":0},"i":{"x":1,"y":1},"s":[100,100],"t":36.06000143336132},{"s":[100,100],"t":36.090001434786245}]},"p":{"a":1,"k":[{"o":{"x":0.65,"y":0},"i":{"x":0.35,"y":0},"s":[6.15,8.63],"t":0},{"o":{"x":0.65,"y":0},"i":{"x":0.35,"y":0},"s":[6.15,8.63],"t":0.03000000142492354},{"o":{"x":0.65,"y":0},"i":{"x":0.35,"y":0},"s":[8.82,8.82],"t":18.03000071668066},{"o":{"x":0.65,"y":0},"i":{"x":0.35,"y":0},"s":[8.82,8.82],"t":18.060000718105584},{"o":{"x":0,"y":0},"i":{"x":1,"y":1},"s":[6.15,8.63],"t":36.06000143336132},{"s":[6.15,8.63],"t":36.090001434786245}]},"r":{"a":1,"k":[{"o":{"x":0.65,"y":0},"i":{"x":0.35,"y":0},"s":[-60],"t":0},{"o":{"x":0.65,"y":0},"i":{"x":0.35,"y":0},"s":[-60],"t":0.03000000142492354},{"o":{"x":0.65,"y":0},"i":{"x":0.35,"y":0},"s":[-45],"t":18.03000071668066},{"o":{"x":0.65,"y":0},"i":{"x":0.35,"y":0},"s":[-45],"t":18.060000718105584},{"o":{"x":0,"y":0},"i":{"x":1,"y":1},"s":[-60],"t":36.06000143336132},{"s":[-60],"t":36.090001434786245}]},"o":{"a":1,"k":[{"o":{"x":0.65,"y":0},"i":{"x":0.35,"y":0},"s":[100],"t":0},{"o":{"x":0.65,"y":0},"i":{"x":0.35,"y":0},"s":[100],"t":0.03000000142492354},{"o":{"x":0.65,"y":0},"i":{"x":0.35,"y":0},"s":[100],"t":18.03000071668066},{"o":{"x":0.65,"y":0},"i":{"x":0.35,"y":0},"s":[100],"t":18.060000718105584},{"o":{"x":0,"y":0},"i":{"x":1,"y":1},"s":[100],"t":36.06000143336132},{"s":[100],"t":36.090001434786245}]}},"shapes":[{"ty":"sh","d":1,"ks":{"a":1,"k":[{"o":{"x":0.65,"y":0},"i":{"x":0.35,"y":0},"s":[{"c":true,"i":[[0,0],[-0.55,0],[0,0],[0,-0.55],[0,0],[0.55,0],[0,0],[0,0.55]],"o":[[0,-0.55],[0,0],[0.55,0],[0,0],[0,0.55],[0,0],[-0.55,0],[0,0]],"v":[[0,1],[1,0],[4,0],[5,1],[5,5.5],[4,6.5],[1,6.5],[0,5.5]]}],"t":0},{"o":{"x":0.65,"y":0},"i":{"x":0.35,"y":0},"s":[{"c":true,"i":[[0,0],[-0.55,0],[0,0],[0,-0.55],[0,0],[0.55,0],[0,0],[0,0.55]],"o":[[0,-0.55],[0,0],[0.55,0],[0,0],[0,0.55],[0,0],[-0.55,0],[0,0]],"v":[[0,1],[1,0],[4,0],[5,1],[5,5.5],[4,6.5],[1,6.5],[0,5.5]]}],"t":0.03000000142492354},{"o":{"x":0.65,"y":0},"i":{"x":0.35,"y":0},"s":[{"c":true,"i":[[0,0],[0,0],[0,0],[0,0],[0,0],[0,0],[0,0],[0,0]],"o":[[0,0],[0,0],[0,0],[0,0],[0,0],[0,0],[0,0],[0,0]],"v":[[0,0],[0,0],[2,0],[2,0],[2,9],[2,9],[0,9],[0,9]]}],"t":18.03000071668066},{"o":{"x":0.65,"y":0},"i":{"x":0.35,"y":0},"s":[{"c":true,"i":[[0,0],[0,0],[0,0],[0,0],[0,0],[0,0],[0,0],[0,0]],"o":[[0,0],[0,0],[0,0],[0,0],[0,0],[0,0],[0,0],[0,0]],"v":[[0,0],[0,0],[2,0],[2,0],[2,9],[2,9],[0,9],[0,9]]}],"t":18.060000718105584},{"o":{"x":0,"y":0},"i":{"x":1,"y":1},"s":[{"c":true,"i":[[0,0],[-0.55,0],[0,0],[0,-0.55],[0,0],[0.55,0],[0,0],[0,0.55]],"o":[[0,-0.55],[0,0],[0.55,0],[0,0],[0,0.55],[0,0],[-0.55,0],[0,0]],"v":[[0,1],[1,0],[4,0],[5,1],[5,5.5],[4,6.5],[1,6.5],[0,5.5]]}],"t":36.06000143336132},{"s":[{"c":true,"i":[[0,0],[-0.55,0],[0,0],[0,-0.55],[0,0],[0.55,0],[0,0],[0,0.55]],"o":[[0,-0.55],[0,0],[0.55,0],[0,0],[0,0.55],[0,0],[-0.55,0],[0,0]],"v":[[0,1],[1,0],[4,0],[5,1],[5,5.5],[4,6.5],[1,6.5],[0,5.5]]}],"t":36.090001434786245}]}},{"ty":"fl","c":{"a":1,"k":[{"o":{"x":0.65,"y":0},"i":{"x":0.35,"y":0},"s":[0,0,0],"t":0},{"o":{"x":0.65,"y":0},"i":{"x":0.35,"y":0},"s":[0,0,0],"t":0.03000000142492354},{"o":{"x":0.65,"y":0},"i":{"x":0.35,"y":0},"s":[0,0,0],"t":18.03000071668066},{"o":{"x":0.65,"y":0},"i":{"x":0.35,"y":0},"s":[0,0,0],"t":18.060000718105584},{"o":{"x":0,"y":0},"i":{"x":1,"y":1},"s":[0,0,0],"t":36.06000143336132},{"s":[0,0,0],"t":36.090001434786245}]},"r":1,"o":{"a":1,"k":[{"o":{"x":0.65,"y":0},"i":{"x":0.35,"y":0},"s":[100],"t":0},{"o":{"x":0.65,"y":0},"i":{"x":0.35,"y":0},"s":[100],"t":0.03000000142492354},{"o":{"x":0.65,"y":0},"i":{"x":0.35,"y":0},"s":[100],"t":18.03000071668066},{"o":{"x":0.65,"y":0},"i":{"x":0.35,"y":0},"s":[100],"t":18.060000718105584},{"o":{"x":0,"y":0},"i":{"x":1,"y":1},"s":[100],"t":36.06000143336132},{"s":[100],"t":36.090001434786245}]}}],"ind":5},{"ty":4,"sr":1,"st":0,"op":37.090001434786245,"ip":0,"hasMask":false,"ao":0,"ks":{"a":{"a":1,"k":[{"o":{"x":0.65,"y":0},"i":{"x":0.35,"y":0},"s":[2.5,3.25],"t":0},{"o":{"x":0.65,"y":0},"i":{"x":0.35,"y":0},"s":[2.5,3.25],"t":0.03000000142492354},{"o":{"x":0.65,"y":0},"i":{"x":0.35,"y":0},"s":[1,4.5],"t":18.03000071668066},{"o":{"x":0.65,"y":0},"i":{"x":0.35,"y":0},"s":[1,4.5],"t":18.060000718105584},{"o":{"x":0,"y":0},"i":{"x":1,"y":1},"s":[2.5,3.25],"t":36.06000143336132},{"s":[2.5,3.25],"t":36.090001434786245}]},"s":{"a":1,"k":[{"o":{"x":0.65,"y":0},"i":{"x":0.35,"y":0},"s":[100,100],"t":0},{"o":{"x":0.65,"y":0},"i":{"x":0.35,"y":0},"s":[100,100],"t":0.03000000142492354},{"o":{"x":0.65,"y":0},"i":{"x":0.35,"y":0},"s":[100,100],"t":18.03000071668066},{"o":{"x":0.65,"y":0},"i":{"x":0.35,"y":0},"s":[100,100],"t":18.060000718105584},{"o":{"x":0,"y":0},"i":{"x":1,"y":1},"s":[100,100],"t":36.06000143336132},{"s":[100,100],"t":36.090001434786245}]},"p":{"a":1,"k":[{"o":{"x":0.65,"y":0},"i":{"x":0.35,"y":0},"s":[17.85,8.63],"t":0},{"o":{"x":0.65,"y":0},"i":{"x":0.35,"y":0},"s":[17.85,8.63],"t":0.03000000142492354},{"o":{"x":0.65,"y":0},"i":{"x":0.35,"y":0},"s":[15.18,8.82],"t":18.03000071668066},{"o":{"x":0.65,"y":0},"i":{"x":0.35,"y":0},"s":[15.18,8.82],"t":18.060000718105584},{"o":{"x":0,"y":0},"i":{"x":1,"y":1},"s":[17.85,8.63],"t":36.06000143336132},{"s":[17.85,8.63],"t":36.090001434786245}]},"r":{"a":1,"k":[{"o":{"x":0.65,"y":0},"i":{"x":0.35,"y":0},"s":[60],"t":0},{"o":{"x":0.65,"y":0},"i":{"x":0.35,"y":0},"s":[60],"t":0.03000000142492354},{"o":{"x":0.65,"y":0},"i":{"x":0.35,"y":0},"s":[45],"t":18.03000071668066},{"o":{"x":0.65,"y":0},"i":{"x":0.35,"y":0},"s":[45],"t":18.060000718105584},{"o":{"x":0,"y":0},"i":{"x":1,"y":1},"s":[60],"t":36.06000143336132},{"s":[60],"t":36.090001434786245}]},"o":{"a":1,"k":[{"o":{"x":0.65,"y":0},"i":{"x":0.35,"y":0},"s":[100],"t":0},{"o":{"x":0.65,"y":0},"i":{"x":0.35,"y":0},"s":[100],"t":0.03000000142492354},{"o":{"x":0.65,"y":0},"i":{"x":0.35,"y":0},"s":[100],"t":18.03000071668066},{"o":{"x":0.65,"y":0},"i":{"x":0.35,"y":0},"s":[100],"t":18.060000718105584},{"o":{"x":0,"y":0},"i":{"x":1,"y":1},"s":[100],"t":36.06000143336132},{"s":[100],"t":36.090001434786245}]}},"shapes":[{"ty":"sh","d":1,"ks":{"a":1,"k":[{"o":{"x":0.65,"y":0},"i":{"x":0.35,"y":0},"s":[{"c":true,"i":[[0,0],[-0.55,0],[0,0],[0,-0.55],[0,0],[0.55,0],[0,0],[0,0.55]],"o":[[0,-0.55],[0,0],[0.55,0],[0,0],[0,0.55],[0,0],[-0.55,0],[0,0]],"v":[[0,1],[1,0],[4,0],[5,1],[5,5.5],[4,6.5],[1,6.5],[0,5.5]]}],"t":0},{"o":{"x":0.65,"y":0},"i":{"x":0.35,"y":0},"s":[{"c":true,"i":[[0,0],[-0.55,0],[0,0],[0,-0.55],[0,0],[0.55,0],[0,0],[0,0.55]],"o":[[0,-0.55],[0,0],[0.55,0],[0,0],[0,0.55],[0,0],[-0.55,0],[0,0]],"v":[[0,1],[1,0],[4,0],[5,1],[5,5.5],[4,6.5],[1,6.5],[0,5.5]]}],"t":0.03000000142492354},{"o":{"x":0.65,"y":0},"i":{"x":0.35,"y":0},"s":[{"c":true,"i":[[0,0],[0,0],[0,0],[0,0],[0,0],[0,0],[0,0],[0,0]],"o":[[0,0],[0,0],[0,0],[0,0],[0,0],[0,0],[0,0],[0,0]],"v":[[0,0],[0,0],[2,0],[2,0],[2,9],[2,9],[0,9],[0,9]]}],"t":18.03000071668066},{"o":{"x":0.65,"y":0},"i":{"x":0.35,"y":0},"s":[{"c":true,"i":[[0,0],[0,0],[0,0],[0,0],[0,0],[0,0],[0,0],[0,0]],"o":[[0,0],[0,0],[0,0],[0,0],[0,0],[0,0],[0,0],[0,0]],"v":[[0,0],[0,0],[2,0],[2,0],[2,9],[2,9],[0,9],[0,9]]}],"t":18.060000718105584},{"o":{"x":0,"y":0},"i":{"x":1,"y":1},"s":[{"c":true,"i":[[0,0],[-0.55,0],[0,0],[0,-0.55],[0,0],[0.55,0],[0,0],[0,0.55]],"o":[[0,-0.55],[0,0],[0.55,0],[0,0],[0,0.55],[0,0],[-0.55,0],[0,0]],"v":[[0,1],[1,0],[4,0],[5,1],[5,5.5],[4,6.5],[1,6.5],[0,5.5]]}],"t":36.06000143336132},{"s":[{"c":true,"i":[[0,0],[-0.55,0],[0,0],[0,-0.55],[0,0],[0.55,0],[0,0],[0,0.55]],"o":[[0,-0.55],[0,0],[0.55,0],[0,0],[0,0.55],[0,0],[-0.55,0],[0,0]],"v":[[0,1],[1,0],[4,0],[5,1],[5,5.5],[4,6.5],[1,6.5],[0,5.5]]}],"t":36.090001434786245}]}},{"ty":"fl","c":{"a":1,"k":[{"o":{"x":0.65,"y":0},"i":{"x":0.35,"y":0},"s":[0,0,0],"t":0},{"o":{"x":0.65,"y":0},"i":{"x":0.35,"y":0},"s":[0,0,0],"t":0.03000000142492354},{"o":{"x":0.65,"y":0},"i":{"x":0.35,"y":0},"s":[0,0,0],"t":18.03000071668066},{"o":{"x":0.65,"y":0},"i":{"x":0.35,"y":0},"s":[0,0,0],"t":18.060000718105584},{"o":{"x":0,"y":0},"i":{"x":1,"y":1},"s":[0,0,0],"t":36.06000143336132},{"s":[0,0,0],"t":36.090001434786245}]},"r":1,"o":{"a":1,"k":[{"o":{"x":0.65,"y":0},"i":{"x":0.35,"y":0},"s":[100],"t":0},{"o":{"x":0.65,"y":0},"i":{"x":0.35,"y":0},"s":[100],"t":0.03000000142492354},{"o":{"x":0.65,"y":0},"i":{"x":0.35,"y":0},"s":[100],"t":18.03000071668066},{"o":{"x":0.65,"y":0},"i":{"x":0.35,"y":0},"s":[100],"t":18.060000718105584},{"o":{"x":0,"y":0},"i":{"x":1,"y":1},"s":[100],"t":36.06000143336132},{"s":[100],"t":36.090001434786245}]}}],"ind":6},{"ty":4,"sr":1,"st":0,"op":37.090001434786245,"ip":0,"hasMask":false,"ao":0,"ks":{"a":{"a":1,"k":[{"o":{"x":0.65,"y":0},"i":{"x":0.35,"y":0},"s":[2.5,3.25],"t":0},{"o":{"x":0.65,"y":0},"i":{"x":0.35,"y":0},"s":[2.5,3.25],"t":0.03000000142492354},{"o":{"x":0.65,"y":0},"i":{"x":0.35,"y":0},"s":[1,0.5],"t":18.03000071668066},{"o":{"x":0.65,"y":0},"i":{"x":0.35,"y":0},"s":[1,0.5],"t":18.060000718105584},{"o":{"x":0,"y":0},"i":{"x":1,"y":1},"s":[2.5,3.25],"t":36.06000143336132},{"s":[2.5,3.25],"t":36.090001434786245}]},"s":{"a":1,"k":[{"o":{"x":0.65,"y":0},"i":{"x":0.35,"y":0},"s":[100,100],"t":0},{"o":{"x":0.65,"y":0},"i":{"x":0.35,"y":0},"s":[100,100],"t":0.03000000142492354},{"o":{"x":0.65,"y":0},"i":{"x":0.35,"y":0},"s":[100,100],"t":18.03000071668066},{"o":{"x":0.65,"y":0},"i":{"x":0.35,"y":0},"s":[100,100],"t":18.060000718105584},{"o":{"x":0,"y":0},"i":{"x":1,"y":1},"s":[100,100],"t":36.06000143336132},{"s":[100,100],"t":36.090001434786245}]},"p":{"a":1,"k":[{"o":{"x":0.65,"y":0},"i":{"x":0.35,"y":0},"s":[12,5.25],"t":0},{"o":{"x":0.65,"y":0},"i":{"x":0.35,"y":0},"s":[12,5.25],"t":0.03000000142492354},{"o":{"x":0.65,"y":0},"i":{"x":0.35,"y":0},"s":[12,11.5],"t":18.03000071668066},{"o":{"x":0.65,"y":0},"i":{"x":0.35,"y":0},"s":[12,11.5],"t":18.060000718105584},{"o":{"x":0,"y":0},"i":{"x":1,"y":1},"s":[12,5.25],"t":36.06000143336132},{"s":[12,5.25],"t":36.090001434786245}]},"r":{"a":1,"k":[{"o":{"x":0.65,"y":0},"i":{"x":0.35,"y":0},"s":[0],"t":0},{"o":{"x":0.65,"y":0},"i":{"x":0.35,"y":0},"s":[0],"t":0.03000000142492354},{"o":{"x":0.65,"y":0},"i":{"x":0.35,"y":0},"s":[0],"t":18.03000071668066},{"o":{"x":0.65,"y":0},"i":{"x":0.35,"y":0},"s":[0],"t":18.060000718105584},{"o":{"x":0,"y":0},"i":{"x":1,"y":1},"s":[0],"t":36.06000143336132},{"s":[0],"t":36.090001434786245}]},"o":{"a":1,"k":[{"o":{"x":0.65,"y":0},"i":{"x":0.35,"y":0},"s":[100],"t":0},{"o":{"x":0.65,"y":0},"i":{"x":0.35,"y":0},"s":[100],"t":0.03000000142492354},{"o":{"x":0.65,"y":0},"i":{"x":0.35,"y":0},"s":[100],"t":18.03000071668066},{"o":{"x":0.65,"y":0},"i":{"x":0.35,"y":0},"s":[100],"t":18.060000718105584},{"o":{"x":0,"y":0},"i":{"x":1,"y":1},"s":[100],"t":36.06000143336132},{"s":[100],"t":36.090001434786245}]}},"shapes":[{"ty":"sh","d":1,"ks":{"a":1,"k":[{"o":{"x":0.65,"y":0},"i":{"x":0.35,"y":0},"s":[{"c":true,"i":[[0,0],[-0.55,0],[0,0],[0,-0.55],[0,0],[0.55,0],[0,0],[0,0.55]],"o":[[0,-0.55],[0,0],[0.55,0],[0,0],[0,0.55],[0,0],[-0.55,0],[0,0]],"v":[[0,1],[1,0],[4,0],[5,1],[5,5.5],[4,6.5],[1,6.5],[0,5.5]]}],"t":0},{"o":{"x":0.65,"y":0},"i":{"x":0.35,"y":0},"s":[{"c":true,"i":[[0,0],[-0.55,0],[0,0],[0,-0.55],[0,0],[0.55,0],[0,0],[0,0.55]],"o":[[0,-0.55],[0,0],[0.55,0],[0,0],[0,0.55],[0,0],[-0.55,0],[0,0]],"v":[[0,1],[1,0],[4,0],[5,1],[5,5.5],[4,6.5],[1,6.5],[0,5.5]]}],"t":0.03000000142492354},{"o":{"x":0.65,"y":0},"i":{"x":0.35,"y":0},"s":[{"c":true,"i":[[0,0],[0,0],[0,0],[0,0],[0,0],[0,0],[0,0],[0,0]],"o":[[0,0],[0,0],[0,0],[0,0],[0,0],[0,0],[0,0],[0,0]],"v":[[0,0],[0,0],[2,0],[2,0],[2,1],[2,1],[0,1],[0,1]]}],"t":18.03000071668066},{"o":{"x":0.65,"y":0},"i":{"x":0.35,"y":0},"s":[{"c":true,"i":[[0,0],[0,0],[0,0],[0,0],[0,0],[0,0],[0,0],[0,0]],"o":[[0,0],[0,0],[0,0],[0,0],[0,0],[0,0],[0,0],[0,0]],"v":[[0,0],[0,0],[2,0],[2,0],[2,1],[2,1],[0,1],[0,1]]}],"t":18.060000718105584},{"o":{"x":0,"y":0},"i":{"x":1,"y":1},"s":[{"c":true,"i":[[0,0],[-0.55,0],[0,0],[0,-0.55],[0,0],[0.55,0],[0,0],[0,0.55]],"o":[[0,-0.55],[0,0],[0.55,0],[0,0],[0,0.55],[0,0],[-0.55,0],[0,0]],"v":[[0,1],[1,0],[4,0],[5,1],[5,5.5],[4,6.5],[1,6.5],[0,5.5]]}],"t":36.06000143336132},{"s":[{"c":true,"i":[[0,0],[-0.55,0],[0,0],[0,-0.55],[0,0],[0.55,0],[0,0],[0,0.55]],"o":[[0,-0.55],[0,0],[0.55,0],[0,0],[0,0.55],[0,0],[-0.55,0],[0,0]],"v":[[0,1],[1,0],[4,0],[5,1],[5,5.5],[4,6.5],[1,6.5],[0,5.5]]}],"t":36.090001434786245}]}},{"ty":"fl","c":{"a":1,"k":[{"o":{"x":0.65,"y":0},"i":{"x":0.35,"y":0},"s":[0,0,0],"t":0},{"o":{"x":0.65,"y":0},"i":{"x":0.35,"y":0},"s":[0,0,0],"t":0.03000000142492354},{"o":{"x":0.65,"y":0},"i":{"x":0.35,"y":0},"s":[0,0,0],"t":18.03000071668066},{"o":{"x":0.65,"y":0},"i":{"x":0.35,"y":0},"s":[0,0,0],"t":18.060000718105584},{"o":{"x":0,"y":0},"i":{"x":1,"y":1},"s":[0,0,0],"t":36.06000143336132},{"s":[0,0,0],"t":36.090001434786245}]},"r":1,"o":{"a":1,"k":[{"o":{"x":0.65,"y":0},"i":{"x":0.35,"y":0},"s":[100],"t":0},{"o":{"x":0.65,"y":0},"i":{"x":0.35,"y":0},"s":[100],"t":0.03000000142492354},{"o":{"x":0.65,"y":0},"i":{"x":0.35,"y":0},"s":[100],"t":18.03000071668066},{"o":{"x":0.65,"y":0},"i":{"x":0.35,"y":0},"s":[100],"t":18.060000718105584},{"o":{"x":0,"y":0},"i":{"x":1,"y":1},"s":[100],"t":36.06000143336132},{"s":[100],"t":36.090001434786245}]}}],"ind":7},{"ty":4,"sr":1,"st":0,"op":37.090001434786245,"ip":0,"hasMask":false,"ao":0,"ks":{"a":{"a":1,"k":[{"o":{"x":0.65,"y":0},"i":{"x":0.35,"y":0},"s":[9.73,10],"t":0},{"o":{"x":0.65,"y":0},"i":{"x":0.35,"y":0},"s":[9.73,10],"t":0.03000000142492354},{"o":{"x":0.65,"y":0},"i":{"x":0.35,"y":0},"s":[1,1],"t":18.03000071668066},{"o":{"x":0.65,"y":0},"i":{"x":0.35,"y":0},"s":[1,1],"t":18.060000718105584},{"o":{"x":0,"y":0},"i":{"x":1,"y":1},"s":[9.73,10],"t":36.06000143336132},{"s":[9.73,10],"t":36.090001434786245}]},"s":{"a":1,"k":[{"o":{"x":0.65,"y":0},"i":{"x":0.35,"y":0},"s":[100,100],"t":0},{"o":{"x":0.65,"y":0},"i":{"x":0.35,"y":0},"s":[100,100],"t":0.03000000142492354},{"o":{"x":0.65,"y":0},"i":{"x":0.35,"y":0},"s":[100,100],"t":18.03000071668066},{"o":{"x":0.65,"y":0},"i":{"x":0.35,"y":0},"s":[100,100],"t":18.060000718105584},{"o":{"x":0,"y":0},"i":{"x":1,"y":1},"s":[100,100],"t":36.06000143336132},{"s":[100,100],"t":36.090001434786245}]},"p":{"a":1,"k":[{"o":{"x":0.65,"y":0},"i":{"x":0.35,"y":0},"s":[12,12],"t":0},{"o":{"x":0.65,"y":0},"i":{"x":0.35,"y":0},"s":[12,12],"t":0.03000000142492354},{"o":{"x":0.65,"y":0},"i":{"x":0.35,"y":0},"s":[12,12],"t":18.03000071668066},{"o":{"x":0.65,"y":0},"i":{"x":0.35,"y":0},"s":[12,12],"t":18.060000718105584},{"o":{"x":0,"y":0},"i":{"x":1,"y":1},"s":[12,12],"t":36.06000143336132},{"s":[12,12],"t":36.090001434786245}]},"r":{"a":1,"k":[{"o":{"x":0.65,"y":0},"i":{"x":0.35,"y":0},"s":[0],"t":0},{"o":{"x":0.65,"y":0},"i":{"x":0.35,"y":0},"s":[0],"t":0.03000000142492354},{"o":{"x":0.65,"y":0},"i":{"x":0.35,"y":0},"s":[0],"t":18.03000071668066},{"o":{"x":0.65,"y":0},"i":{"x":0.35,"y":0},"s":[0],"t":18.060000718105584},{"o":{"x":0,"y":0},"i":{"x":1,"y":1},"s":[0],"t":36.06000143336132},{"s":[0],"t":36.090001434786245}]},"o":{"a":1,"k":[{"o":{"x":0.65,"y":0},"i":{"x":0.35,"y":0},"s":[100],"t":0},{"o":{"x":0.65,"y":0},"i":{"x":0.35,"y":0},"s":[100],"t":0.03000000142492354},{"o":{"x":0.65,"y":0},"i":{"x":0.35,"y":0},"s":[100],"t":18.03000071668066},{"o":{"x":0.65,"y":0},"i":{"x":0.35,"y":0},"s":[100],"t":18.060000718105584},{"o":{"x":0,"y":0},"i":{"x":1,"y":1},"s":[100],"t":36.06000143336132},{"s":[100],"t":36.090001434786245}]}},"shapes":[{"ty":"sh","d":1,"ks":{"a":1,"k":[{"o":{"x":0.65,"y":0},"i":{"x":0.35,"y":0},"s":[{"c":true,"i":[[0,0],[0.66,0.66],[0,0.93],[-0.66,0.66],[-0.93,0],[-0.66,-0.66],[0,-0.93],[0.66,-0.66],[0.93,0]],"o":[[-0.93,0],[-0.66,-0.66],[0,-0.93],[0.66,-0.66],[0.93,0],[0.66,0.66],[0,0.93],[-0.66,0.66],[0,0]],"v":[[9.73,13.5],[7.25,12.47],[6.23,10],[7.25,7.53],[9.73,6.5],[12.2,7.53],[13.23,10],[12.2,12.47],[9.73,13.5]]}],"t":0},{"o":{"x":0.65,"y":0},"i":{"x":0.35,"y":0},"s":[{"c":true,"i":[[0,0],[0.66,0.66],[0,0.93],[-0.66,0.66],[-0.93,0],[-0.66,-0.66],[0,-0.93],[0.66,-0.66],[0.93,0]],"o":[[-0.93,0],[-0.66,-0.66],[0,-0.93],[0.66,-0.66],[0.93,0],[0.66,0.66],[0,0.93],[-0.66,0.66],[0,0]],"v":[[9.73,13.5],[7.25,12.47],[6.23,10],[7.25,7.53],[9.73,6.5],[12.2,7.53],[13.23,10],[12.2,12.47],[9.73,13.5]]}],"t":0.03000000142492354},{"o":{"x":0.65,"y":0},"i":{"x":0.35,"y":0},"s":[{"c":true,"i":[[0,0],[0.07,0.07],[0,0.09],[-0.07,0.07],[-0.1,0],[-0.07,-0.07],[0,-0.09],[0.07,-0.07],[0.1,0]],"o":[[-0.1,0],[-0.07,-0.07],[0,-0.09],[0.07,-0.07],[0.1,0],[0.07,0.07],[0,0.09],[-0.07,0.07],[0,0]],"v":[[1,1.35],[0.75,1.25],[0.64,1],[0.75,0.75],[1,0.65],[1.25,0.75],[1.36,1],[1.25,1.25],[1,1.35]]}],"t":18.03000071668066},{"o":{"x":0.65,"y":0},"i":{"x":0.35,"y":0},"s":[{"c":true,"i":[[0,0],[0.07,0.07],[0,0.09],[-0.07,0.07],[-0.1,0],[-0.07,-0.07],[0,-0.09],[0.07,-0.07],[0.1,0]],"o":[[-0.1,0],[-0.07,-0.07],[0,-0.09],[0.07,-0.07],[0.1,0],[0.07,0.07],[0,0.09],[-0.07,0.07],[0,0]],"v":[[1,1.35],[0.75,1.25],[0.64,1],[0.75,0.75],[1,0.65],[1.25,0.75],[1.36,1],[1.25,1.25],[1,1.35]]}],"t":18.060000718105584},{"o":{"x":0,"y":0},"i":{"x":1,"y":1},"s":[{"c":true,"i":[[0,0],[0.66,0.66],[0,0.93],[-0.66,0.66],[-0.93,0],[-0.66,-0.66],[0,-0.93],[0.66,-0.66],[0.93,0]],"o":[[-0.93,0],[-0.66,-0.66],[0,-0.93],[0.66,-0.66],[0.93,0],[0.66,0.66],[0,0.93],[-0.66,0.66],[0,0]],"v":[[9.73,13.5],[7.25,12.47],[6.23,10],[7.25,7.53],[9.73,6.5],[12.2,7.53],[13.23,10],[12.2,12.47],[9.73,13.5]]}],"t":36.06000143336132},{"s":[{"c":true,"i":[[0,0],[0.66,0.66],[0,0.93],[-0.66,0.66],[-0.93,0],[-0.66,-0.66],[0,-0.93],[0.66,-0.66],[0.93,0]],"o":[[-0.93,0],[-0.66,-0.66],[0,-0.93],[0.66,-0.66],[0.93,0],[0.66,0.66],[0,0.93],[-0.66,0.66],[0,0]],"v":[[9.73,13.5],[7.25,12.47],[6.23,10],[7.25,7.53],[9.73,6.5],[12.2,7.53],[13.23,10],[12.2,12.47],[9.73,13.5]]}],"t":36.090001434786245}]}},{"ty":"sh","d":1,"ks":{"a":1,"k":[{"o":{"x":0.65,"y":0},"i":{"x":0.35,"y":0},"s":[{"c":true,"i":[[0,0],[0,0.33],[0.04,0.34],[0,0],[0.12,0.22],[0,0],[0.22,-0.09],[0,0],[0.63,0.25],[0,0],[0.25,0],[0,0],[0.04,-0.24],[0,0],[0.52,-0.39],[0,0],[0.12,-0.22],[0,0],[-0.19,-0.15],[0,0],[0,-0.33],[-0.04,-0.32],[0,0],[-0.13,-0.22],[0,0],[-0.22,0.08],[0,0],[-0.63,-0.25],[0,0],[-0.25,0],[0,0],[-0.04,0.24],[0,0],[-0.52,0.4],[0,0],[-0.12,0.22],[0,0],[0.19,0.15],[0,0]],"o":[[0.04,-0.32],[0,-0.33],[0,0],[0.19,-0.15],[0,0],[-0.12,-0.22],[0,0],[-0.52,-0.39],[0,0],[-0.04,-0.24],[0,0],[-0.25,0],[0,0],[-0.63,0.25],[0,0],[-0.22,-0.09],[0,0],[-0.13,0.22],[0,0],[-0.04,0.34],[0,0.33],[0,0],[-0.19,0.15],[0,0],[0.12,0.22],[0,0],[0.52,0.4],[0,0],[0.04,0.24],[0,0],[0.25,0],[0,0],[0.63,-0.26],[0,0],[0.22,0.08],[0,0],[0.12,-0.22],[0,0],[0,0]],"v":[[17.16,10.97],[17.23,10],[17.16,9],[19.27,7.37],[19.39,6.73],[17.39,3.27],[16.78,3.05],[14.29,4.05],[12.6,3.07],[12.23,0.42],[11.73,0],[7.73,0],[7.23,0.42],[6.86,3.07],[5.17,4.05],[2.68,3.05],[2.07,3.27],[0.07,6.73],[0.19,7.37],[2.3,9],[2.23,10],[2.3,10.97],[0.19,12.63],[0.07,13.27],[2.07,16.73],[2.68,16.95],[5.17,15.94],[6.86,16.93],[7.23,19.58],[7.73,20],[11.73,20],[12.23,19.58],[12.6,16.93],[14.29,15.94],[16.78,16.95],[17.39,16.73],[19.39,13.27],[19.27,12.63],[17.16,10.97]]}],"t":0},{"o":{"x":0.65,"y":0},"i":{"x":0.35,"y":0},"s":[{"c":true,"i":[[0,0],[0,0.33],[0.04,0.34],[0,0],[0.12,0.22],[0,0],[0.22,-0.09],[0,0],[0.63,0.25],[0,0],[0.25,0],[0,0],[0.04,-0.24],[0,0],[0.52,-0.39],[0,0],[0.12,-0.22],[0,0],[-0.19,-0.15],[0,0],[0,-0.33],[-0.04,-0.32],[0,0],[-0.13,-0.22],[0,0],[-0.22,0.08],[0,0],[-0.63,-0.25],[0,0],[-0.25,0],[0,0],[-0.04,0.24],[0,0],[-0.52,0.4],[0,0],[-0.12,0.22],[0,0],[0.19,0.15],[0,0]],"o":[[0.04,-0.32],[0,-0.33],[0,0],[0.19,-0.15],[0,0],[-0.12,-0.22],[0,0],[-0.52,-0.39],[0,0],[-0.04,-0.24],[0,0],[-0.25,0],[0,0],[-0.63,0.25],[0,0],[-0.22,-0.09],[0,0],[-0.13,0.22],[0,0],[-0.04,0.34],[0,0.33],[0,0],[-0.19,0.15],[0,0],[0.12,0.22],[0,0],[0.52,0.4],[0,0],[0.04,0.24],[0,0],[0.25,0],[0,0],[0.63,-0.26],[0,0],[0.22,0.08],[0,0],[0.12,-0.22],[0,0],[0,0]],"v":[[17.16,10.97],[17.23,10],[17.16,9],[19.27,7.37],[19.39,6.73],[17.39,3.27],[16.78,3.05],[14.29,4.05],[12.6,3.07],[12.23,0.42],[11.73,0],[7.73,0],[7.23,0.42],[6.86,3.07],[5.17,4.05],[2.68,3.05],[2.07,3.27],[0.07,6.73],[0.19,7.37],[2.3,9],[2.23,10],[2.3,10.97],[0.19,12.63],[0.07,13.27],[2.07,16.73],[2.68,16.95],[5.17,15.94],[6.86,16.93],[7.23,19.58],[7.73,20],[11.73,20],[12.23,19.58],[12.6,16.93],[14.29,15.94],[16.78,16.95],[17.39,16.73],[19.39,13.27],[19.27,12.63],[17.16,10.97]]}],"t":0.03000000142492354},{"o":{"x":0.65,"y":0},"i":{"x":0.35,"y":0},"s":[{"c":true,"i":[[0,0],[0,0.03],[0,0.03],[0,0],[0.01,0.02],[0,0],[0.02,-0.01],[0,0],[0.06,0.03],[0,0],[0.03,0],[0,0],[0,-0.02],[0,0],[0.05,-0.04],[0,0],[0.01,-0.02],[0,0],[-0.02,-0.02],[0,0],[0,-0.03],[0,-0.03],[0,0],[-0.01,-0.02],[0,0],[-0.02,0.01],[0,0],[-0.06,-0.02],[0,0],[-0.03,0],[0,0],[0,0.02],[0,0],[-0.05,0.04],[0,0],[-0.01,0.02],[0,0],[0.02,0.02],[0,0]],"o":[[0,-0.03],[0,-0.03],[0,0],[0.02,-0.02],[0,0],[-0.01,-0.02],[0,0],[-0.05,-0.04],[0,0],[0,-0.02],[0,0],[-0.03,0],[0,0],[-0.06,0.03],[0,0],[-0.02,-0.01],[0,0],[-0.01,0.02],[0,0],[0,0.03],[0,0.03],[0,0],[-0.02,0.02],[0,0],[0.01,0.02],[0,0],[0.05,0.04],[0,0],[0,0.02],[0,0],[0.03,0],[0,0],[0.06,-0.03],[0,0],[0.02,0.01],[0,0],[0.01,-0.02],[0,0],[0,0]],"v":[[1.76,1.1],[1.77,1],[1.76,0.9],[1.98,0.74],[1.99,0.67],[1.79,0.33],[1.73,0.31],[1.47,0.41],[1.3,0.31],[1.26,0.04],[1.21,0],[0.79,0],[0.74,0.04],[0.71,0.31],[0.53,0.41],[0.28,0.31],[0.21,0.33],[0.01,0.67],[0.02,0.74],[0.24,0.9],[0.23,1],[0.24,1.1],[0.02,1.26],[0.01,1.33],[0.21,1.67],[0.28,1.7],[0.53,1.59],[0.71,1.69],[0.74,1.96],[0.79,2],[1.21,2],[1.26,1.96],[1.3,1.69],[1.47,1.59],[1.73,1.7],[1.79,1.67],[1.99,1.33],[1.98,1.26],[1.76,1.1]]}],"t":18.03000071668066},{"o":{"x":0.65,"y":0},"i":{"x":0.35,"y":0},"s":[{"c":true,"i":[[0,0],[0,0.03],[0,0.03],[0,0],[0.01,0.02],[0,0],[0.02,-0.01],[0,0],[0.06,0.03],[0,0],[0.03,0],[0,0],[0,-0.02],[0,0],[0.05,-0.04],[0,0],[0.01,-0.02],[0,0],[-0.02,-0.02],[0,0],[0,-0.03],[0,-0.03],[0,0],[-0.01,-0.02],[0,0],[-0.02,0.01],[0,0],[-0.06,-0.02],[0,0],[-0.03,0],[0,0],[0,0.02],[0,0],[-0.05,0.04],[0,0],[-0.01,0.02],[0,0],[0.02,0.02],[0,0]],"o":[[0,-0.03],[0,-0.03],[0,0],[0.02,-0.02],[0,0],[-0.01,-0.02],[0,0],[-0.05,-0.04],[0,0],[0,-0.02],[0,0],[-0.03,0],[0,0],[-0.06,0.03],[0,0],[-0.02,-0.01],[0,0],[-0.01,0.02],[0,0],[0,0.03],[0,0.03],[0,0],[-0.02,0.02],[0,0],[0.01,0.02],[0,0],[0.05,0.04],[0,0],[0,0.02],[0,0],[0.03,0],[0,0],[0.06,-0.03],[0,0],[0.02,0.01],[0,0],[0.01,-0.02],[0,0],[0,0]],"v":[[1.76,1.1],[1.77,1],[1.76,0.9],[1.98,0.74],[1.99,0.67],[1.79,0.33],[1.73,0.31],[1.47,0.41],[1.3,0.31],[1.26,0.04],[1.21,0],[0.79,0],[0.74,0.04],[0.71,0.31],[0.53,0.41],[0.28,0.31],[0.21,0.33],[0.01,0.67],[0.02,0.74],[0.24,0.9],[0.23,1],[0.24,1.1],[0.02,1.26],[0.01,1.33],[0.21,1.67],[0.28,1.7],[0.53,1.59],[0.71,1.69],[0.74,1.96],[0.79,2],[1.21,2],[1.26,1.96],[1.3,1.69],[1.47,1.59],[1.73,1.7],[1.79,1.67],[1.99,1.33],[1.98,1.26],[1.76,1.1]]}],"t":18.060000718105584},{"o":{"x":0,"y":0},"i":{"x":1,"y":1},"s":[{"c":true,"i":[[0,0],[0,0.33],[0.04,0.34],[0,0],[0.12,0.22],[0,0],[0.22,-0.09],[0,0],[0.63,0.25],[0,0],[0.25,0],[0,0],[0.04,-0.24],[0,0],[0.52,-0.39],[0,0],[0.12,-0.22],[0,0],[-0.19,-0.15],[0,0],[0,-0.33],[-0.04,-0.32],[0,0],[-0.13,-0.22],[0,0],[-0.22,0.08],[0,0],[-0.63,-0.25],[0,0],[-0.25,0],[0,0],[-0.04,0.24],[0,0],[-0.52,0.4],[0,0],[-0.12,0.22],[0,0],[0.19,0.15],[0,0]],"o":[[0.04,-0.32],[0,-0.33],[0,0],[0.19,-0.15],[0,0],[-0.12,-0.22],[0,0],[-0.52,-0.39],[0,0],[-0.04,-0.24],[0,0],[-0.25,0],[0,0],[-0.63,0.25],[0,0],[-0.22,-0.09],[0,0],[-0.13,0.22],[0,0],[-0.04,0.34],[0,0.33],[0,0],[-0.19,0.15],[0,0],[0.12,0.22],[0,0],[0.52,0.4],[0,0],[0.04,0.24],[0,0],[0.25,0],[0,0],[0.63,-0.26],[0,0],[0.22,0.08],[0,0],[0.12,-0.22],[0,0],[0,0]],"v":[[17.16,10.97],[17.23,10],[17.16,9],[19.27,7.37],[19.39,6.73],[17.39,3.27],[16.78,3.05],[14.29,4.05],[12.6,3.07],[12.23,0.42],[11.73,0],[7.73,0],[7.23,0.42],[6.86,3.07],[5.17,4.05],[2.68,3.05],[2.07,3.27],[0.07,6.73],[0.19,7.37],[2.3,9],[2.23,10],[2.3,10.97],[0.19,12.63],[0.07,13.27],[2.07,16.73],[2.68,16.95],[5.17,15.94],[6.86,16.93],[7.23,19.58],[7.73,20],[11.73,20],[12.23,19.58],[12.6,16.93],[14.29,15.94],[16.78,16.95],[17.39,16.73],[19.39,13.27],[19.27,12.63],[17.16,10.97]]}],"t":36.06000143336132},{"s":[{"c":true,"i":[[0,0],[0,0.33],[0.04,0.34],[0,0],[0.12,0.22],[0,0],[0.22,-0.09],[0,0],[0.63,0.25],[0,0],[0.25,0],[0,0],[0.04,-0.24],[0,0],[0.52,-0.39],[0,0],[0.12,-0.22],[0,0],[-0.19,-0.15],[0,0],[0,-0.33],[-0.04,-0.32],[0,0],[-0.13,-0.22],[0,0],[-0.22,0.08],[0,0],[-0.63,-0.25],[0,0],[-0.25,0],[0,0],[-0.04,0.24],[0,0],[-0.52,0.4],[0,0],[-0.12,0.22],[0,0],[0.19,0.15],[0,0]],"o":[[0.04,-0.32],[0,-0.33],[0,0],[0.19,-0.15],[0,0],[-0.12,-0.22],[0,0],[-0.52,-0.39],[0,0],[-0.04,-0.24],[0,0],[-0.25,0],[0,0],[-0.63,0.25],[0,0],[-0.22,-0.09],[0,0],[-0.13,0.22],[0,0],[-0.04,0.34],[0,0.33],[0,0],[-0.19,0.15],[0,0],[0.12,0.22],[0,0],[0.52,0.4],[0,0],[0.04,0.24],[0,0],[0.25,0],[0,0],[0.63,-0.26],[0,0],[0.22,0.08],[0,0],[0.12,-0.22],[0,0],[0,0]],"v":[[17.16,10.97],[17.23,10],[17.16,9],[19.27,7.37],[19.39,6.73],[17.39,3.27],[16.78,3.05],[14.29,4.05],[12.6,3.07],[12.23,0.42],[11.73,0],[7.73,0],[7.23,0.42],[6.86,3.07],[5.17,4.05],[2.68,3.05],[2.07,3.27],[0.07,6.73],[0.19,7.37],[2.3,9],[2.23,10],[2.3,10.97],[0.19,12.63],[0.07,13.27],[2.07,16.73],[2.68,16.95],[5.17,15.94],[6.86,16.93],[7.23,19.58],[7.73,20],[11.73,20],[12.23,19.58],[12.6,16.93],[14.29,15.94],[16.78,16.95],[17.39,16.73],[19.39,13.27],[19.27,12.63],[17.16,10.97]]}],"t":36.090001434786245}]}},{"ty":"fl","c":{"a":1,"k":[{"o":{"x":0.65,"y":0},"i":{"x":0.35,"y":0},"s":[0,0,0],"t":0},{"o":{"x":0.65,"y":0},"i":{"x":0.35,"y":0},"s":[0,0,0],"t":0.03000000142492354},{"o":{"x":0.65,"y":0},"i":{"x":0.35,"y":0},"s":[0,0,0],"t":18.03000071668066},{"o":{"x":0.65,"y":0},"i":{"x":0.35,"y":0},"s":[0,0,0],"t":18.060000718105584},{"o":{"x":0,"y":0},"i":{"x":1,"y":1},"s":[0,0,0],"t":36.06000143336132},{"s":[0,0,0],"t":36.090001434786245}]},"r":1,"o":{"a":1,"k":[{"o":{"x":0.65,"y":0},"i":{"x":0.35,"y":0},"s":[100],"t":0},{"o":{"x":0.65,"y":0},"i":{"x":0.35,"y":0},"s":[100],"t":0.03000000142492354},{"o":{"x":0.65,"y":0},"i":{"x":0.35,"y":0},"s":[100],"t":18.03000071668066},{"o":{"x":0.65,"y":0},"i":{"x":0.35,"y":0},"s":[100],"t":18.060000718105584},{"o":{"x":0,"y":0},"i":{"x":1,"y":1},"s":[100],"t":36.06000143336132},{"s":[100],"t":36.090001434786245}]}}],"ind":8},{"ty":1,"sr":1,"st":0,"op":37.090001434786245,"ip":0,"hasMask":false,"ao":0,"ks":{"a":{"a":0,"k":[0,0]},"s":{"a":0,"k":[100,100]},"p":{"a":0,"k":[0,0]},"r":{"a":0,"k":0},"o":{"a":0,"k":100}},"sc":"#ffffff","sh":24,"sw":24,"ind":9}],"v":"5.7.0","fr":30,"op":36.090001434786245,"ip":0,"assets":[]}